pybuoy/__init__.py
pybuoy/api/base.py
pybuoy/api/forecasts.py
pybuoy/api/realtime.py
pybuoy/api/stations.py
pybuoy/buoy.py
pybuoy/const.py
pybuoy/endpoints.py
pybuoy/exceptions.py
pybuoy/mixins/noaa.xsl
pybuoy/mixins/parser.py
pybuoy/observation/__init__.py
pybuoy/observation/meta.py
pybuoy/observation/observation.py
pybuoy/observation/observation_datum.py
pybuoy/observation/observations.py
pybuoy/py.typed
pybuoy/unit_mappings.py
pybuoy-0.5.9.dist-info/LICENSE
pybuoy-0.5.9.dist-info/METADATA
pybuoy-0.5.9.dist-info/WHEEL
pybuoy-0.5.9.dist-info/RECORD
