Metadata-Version: 2.3
Name: pybuoy
Version: 0.5.9
Summary: Python wrapper for NOAA and NDBC REST web services.
License: GPL-3.0-or-later
Keywords: NDBC,NOAA,api,buoy,weather,wrapper
Author: Kyle J. Burda
Author-email: kylejbdev@gmail.com
Requires-Python: >=3.11
Classifier: Operating System :: OS Independent
Classifier: Programming Language :: Python :: 3.11
Requires-Dist: lxml (>=6.0,<7.0)
Requires-Dist: requests (>=2.32.4,<3.0.0)
Project-URL: Bug Tracker, https://github.com/clairBuoyant/pybuoy/issues
Project-URL: Source Code, https://github.com/clairBuoyant/pybuoy
